ch/__init__.py
ch/zbindenonline/__init__.py
ch/zbindenonline/picture/__init__.py
ch/zbindenonline/picture/crop.py
ch.zbindenonline.picture-0.0.2.dist-info/LICENSE
ch.zbindenonline.picture-0.0.2.dist-info/METADATA
ch.zbindenonline.picture-0.0.2.dist-info/WHEEL
ch.zbindenonline.picture-0.0.2.dist-info/entry_points.txt
ch.zbindenonline.picture-0.0.2.dist-info/top_level.txt
ch.zbindenonline.picture-0.0.2.dist-info/RECORD
