Metadata-Version: 2.1
Name: ch.zbindenonline.picture
Version: 0.0.2
Summary: A library to handle pictures
Home-page: UNKNOWN
Author: Patrick Zbinden
Author-email: patrick+dev@zbinden-online.ch
License: MIT
Platform: UNKNOWN
Classifier: Programming Language :: Python :: 3
Requires-Dist: Pillow
Requires-Dist: click
